{
  "Description": "Detects execution and usage of the DSInternals PowerShell module. Which can be used to perform what might be considered as suspicious activity such as dumping DPAPI backup keys or manipulating NTDS.DIT files.\nThe DSInternals PowerShell Module exposes several internal features of Active Directory and Azure Active Directory. These include FIDO2 and NGC key auditing, offline ntds.dit file manipulation, password auditing, DC recovery from IFM backups and password hash calculation.\n\n\nAuthor: Nasreddine Bencherchali (Nextron Systems)\nSigma Repository: [GitHub](https://github.com/SigmaHQ/sigma)",
  "ID": "846c7a87-8e14-4569-9d49-ecfd4276a01c",
  "InsertDate": "2025-01-25T21:21:23Z",
  "LastUpdateDate": "2025-01-25T21:21:23Z",
  "Level": "high",
  "Name": "DSInternals Suspicious PowerShell Cmdlets - ScriptBlock",
  "Query": "sourcetype like 'windows-%' eql select * from _source_ where (scriptblocktext like '%Add-ADDBSidHistory%' or scriptblocktext like '%Add-ADNgcKey%' or scriptblocktext like '%Add-ADReplNgcKey%' or scriptblocktext like '%ConvertFrom-ADManagedPasswordBlob%' or scriptblocktext like '%ConvertFrom-GPPrefPassword%' or scriptblocktext like '%ConvertFrom-ManagedPasswordBlob%' or scriptblocktext like '%ConvertFrom-UnattendXmlPassword%' or scriptblocktext like '%ConvertFrom-UnicodePassword%' or scriptblocktext like '%ConvertTo-AADHash%' or scriptblocktext like '%ConvertTo-GPPrefPassword%' or scriptblocktext like '%ConvertTo-KerberosKey%' or scriptblocktext like '%ConvertTo-LMHash%' or scriptblocktext like '%ConvertTo-MsoPasswordHash%' or scriptblocktext like '%ConvertTo-NTHash%' or scriptblocktext like '%ConvertTo-OrgIdHash%' or scriptblocktext like '%ConvertTo-UnicodePassword%' or scriptblocktext like '%Disable-ADDBAccount%' or scriptblocktext like '%Enable-ADDBAccount%' or scriptblocktext like '%Get-ADDBAccount%' or scriptblocktext like '%Get-ADDBBackupKey%' or scriptblocktext like '%Get-ADDBDomainController%' or scriptblocktext like '%Get-ADDBGroupManagedServiceAccount%' or scriptblocktext like '%Get-ADDBKdsRootKey%' or scriptblocktext like '%Get-ADDBSchemaAttribute%' or scriptblocktext like '%Get-ADDBServiceAccount%' or scriptblocktext like '%Get-ADDefaultPasswordPolicy%' or scriptblocktext like '%Get-ADKeyCredential%' or scriptblocktext like '%Get-ADPasswordPolicy%' or scriptblocktext like '%Get-ADReplAccount%' or scriptblocktext like '%Get-ADReplBackupKey%' or scriptblocktext like '%Get-ADReplicationAccount%' or scriptblocktext like '%Get-ADSIAccount%' or scriptblocktext like '%Get-AzureADUserEx%' or scriptblocktext like '%Get-BootKey%' or scriptblocktext like '%Get-KeyCredential%' or scriptblocktext like '%Get-LsaBackupKey%' or scriptblocktext like '%Get-LsaPolicy%' or scriptblocktext like '%Get-SamPasswordPolicy%' or scriptblocktext like '%Get-SysKey%' or scriptblocktext like '%Get-SystemKey%' or scriptblocktext like '%New-ADDBRestoreFromMediaScript%' or scriptblocktext like '%New-ADKeyCredential%' or scriptblocktext like '%New-ADNgcKey%' or scriptblocktext like '%New-NTHashSet%' or scriptblocktext like '%Remove-ADDBObject%' or scriptblocktext like '%Save-DPAPIBlob%' or scriptblocktext like '%Set-ADAccountPasswordHash%' or scriptblocktext like '%Set-ADDBAccountPassword%' or scriptblocktext like '%Set-ADDBBootKey%' or scriptblocktext like '%Set-ADDBDomainController%' or scriptblocktext like '%Set-ADDBPrimaryGroup%' or scriptblocktext like '%Set-ADDBSysKey%' or scriptblocktext like '%Set-AzureADUserEx%' or scriptblocktext like '%Set-LsaPolicy%' or scriptblocktext like '%Set-SamAccountPasswordHash%' or scriptblocktext like '%Set-WinUserPasswordHash%' or scriptblocktext like '%Test-ADDBPasswordQuality%' or scriptblocktext like '%Test-ADPasswordQuality%' or scriptblocktext like '%Test-ADReplPasswordQuality%' or scriptblocktext like '%Test-PasswordQuality%' or scriptblocktext like '%Unlock-ADDBAccount%' or scriptblocktext like '%Write-ADNgcKey%' or scriptblocktext like '%Write-ADReplNgcKey%')",
  "Tags": [
    "attack.execution",
    "attack.t1059.001"
  ],
  "Version": "0.1"
}