{
  "Description": "Detects execution and usage of the DSInternals PowerShell module. Which can be used to perform what might be considered as suspicious activity such as dumping DPAPI backup keys or manipulating NTDS.DIT files.\nThe DSInternals PowerShell Module exposes several internal features of Active Directory and Azure Active Directory. These include FIDO2 and NGC key auditing, offline ntds.dit file manipulation, password auditing, DC recovery from IFM backups and password hash calculation.\n\n\nAuthor: Nasreddine Bencherchali (Nextron Systems), Nounou Mbeiri\nSigma Repository: [GitHub](https://github.com/SigmaHQ/sigma)",
  "ID": "43d91656-a9b2-4541-b7e2-6a9bd3a13f4e",
  "InsertDate": "2025-01-21T09:28:56Z",
  "LastUpdateDate": "2025-01-21T09:28:56Z",
  "Level": "high",
  "Name": "DSInternals Suspicious PowerShell Cmdlets",
  "Query": "sourcetype='windows-sysmon' eql select * from _source_ where (command like '%add-addbsidhistory%' or command like '%add-adngckey%' or command like '%add-adreplngckey%' or command like '%convertfrom-admanagedpasswordblob%' or command like '%convertfrom-gpprefpassword%' or command like '%convertfrom-managedpasswordblob%' or command like '%convertfrom-unattendxmlpassword%' or command like '%convertfrom-unicodepassword%' or command like '%convertto-aadhash%' or command like '%convertto-gpprefpassword%' or command like '%convertto-kerberoskey%' or command like '%convertto-lmhash%' or command like '%convertto-msopasswordhash%' or command like '%convertto-nthash%' or command like '%convertto-orgidhash%' or command like '%convertto-unicodepassword%' or command like '%disable-addbaccount%' or command like '%enable-addbaccount%' or command like '%get-addbaccount%' or command like '%get-addbbackupkey%' or command like '%get-addbdomaincontroller%' or command like '%get-addbgroupmanagedserviceaccount%' or command like '%get-addbkdsrootkey%' or command like '%get-addbschemaattribute%' or command like '%get-addbserviceaccount%' or command like '%get-addefaultpasswordpolicy%' or command like '%get-adkeycredential%' or command like '%get-adpasswordpolicy%' or command like '%get-adreplaccount%' or command like '%get-adreplbackupkey%' or command like '%get-adreplicationaccount%' or command like '%get-adsiaccount%' or command like '%get-azureaduserex%' or command like '%get-bootkey%' or command like '%get-keycredential%' or command like '%get-lsabackupkey%' or command like '%get-lsapolicy%' or command like '%get-sampasswordpolicy%' or command like '%get-syskey%' or command like '%get-systemkey%' or command like '%new-addbrestorefrommediascript%' or command like '%new-adkeycredential%' or command like '%new-adngckey%' or command like '%new-nthashset%' or command like '%remove-addbobject%' or command like '%save-dpapiblob%' or command like '%set-adaccountpasswordhash%' or command like '%set-addbaccountpassword%' or command like '%set-addbbootkey%' or command like '%set-addbdomaincontroller%' or command like '%set-addbprimarygroup%' or command like '%set-addbsyskey%' or command like '%set-azureaduserex%' or command like '%set-lsapolicy%' or command like '%set-samaccountpasswordhash%' or command like '%set-winuserpasswordhash%' or command like '%test-addbpasswordquality%' or command like '%test-adpasswordquality%' or command like '%test-adreplpasswordquality%' or command like '%test-passwordquality%' or command like '%unlock-addbaccount%' or command like '%write-adngckey%' or command like '%write-adreplngckey%')",
  "Tags": [
    "attack.execution",
    "attack.t1059.001"
  ],
  "Version": "0.1"
}