{
  "Description": "Detects image load events with revoked certificates by code integrity.\n\nAuthor: Nasreddine Bencherchali (Nextron Systems)\nSigma Repository: [GitHub](https://github.com/SigmaHQ/sigma)",
  "ID": "881b7725-47cc-4055-8000-425823344c59",
  "InsertDate": "2025-02-03T20:32:07Z",
  "LastUpdateDate": "2025-02-03T20:32:07Z",
  "Level": "high",
  "Name": "CodeIntegrity - Revoked Image Loaded",
  "Query": "sourcetype=\"windows-codeintegrity-operational\" (eventid=\"3032\" OR eventid=\"3035\")",
  "Tags": [
    "attack.privilege-escalation"
  ],
  "Version": "0.1"
}